PSAPP/__init__.py
PSAPP/applications-details.yaml
PSAPP/appsReader.py
PSAPP/dataEncryption.py
PSAPP/ecc-configs.yaml
PSAPP/main.py
PSAPP/requirements.txt
PSAPP/test.py
PSAPP/DB/__init__.py
PSAPP/DB/createSchemas.py
PSAPP/DB/createTablespaces.py
PSAPP/DB/dbBaker.py
PSAPP/DB/dbConnection.py
PSAPP/DB/importDumps.py
PSAPP/DB/sshConnection.py
PSAPP/DB/resources/adminUser.sql
PSAPP/DB/resources/appUser.sql
PSAPP/DB/resources/disableConstraints.sql
PSAPP/DB/resources/enableConstraints.sql
PSAPP/DB/resources/instantclient_linux.zip
PSAPP/DB/resources/instantclient_windows.zip
PSAPP/DB/resources/rootUser.sql
PSAPP/DB/resources/secUser.sql
PSAPP/DB/resources/systemUser.sql
PSAPP/DB/resources/tablespace.sql
PSAPP/DB/resources/unifiedSecGrants.sql
PSAPP/Logging/__init__.py
PSAPP/Logging/loggingModule.py
PSAPP/ReleaseProcess/HTMLParser.py
PSAPP/ReleaseProcess/__init__.py
PSAPP/ReleaseProcess/configureModules.py
PSAPP/ReleaseProcess/configureTomcat.py
PSAPP/ReleaseProcess/eccReleaseBaker.py
PSAPP/ReleaseProcess/treeBuilder.py
PSAPP/Validation/__init__.py
PSAPP/Validation/configParser.py
PSAPP/Validation/validationConfig.py
PSAPP-1.0.1.dist-info/METADATA
PSAPP-1.0.1.dist-info/WHEEL
PSAPP-1.0.1.dist-info/entry_points.txt
PSAPP-1.0.1.dist-info/top_level.txt
PSAPP-1.0.1.dist-info/RECORD
