Metadata-Version: 2.1
Name: PSAPP
Version: 1.0.1
Summary: PS Automation deployment tool
Home-page: https://gitlab.com/progressoft/support/scripts/ecc-automation-deployment/
Author: ProgressSoft
License: MIT
Platform: UNKNOWN
Classifier: Programming Language :: Python :: 3
Classifier: License :: OSI Approved :: MIT License
Classifier: Operating System :: OS Independent
Requires-Python: >=3.7
Requires-Dist: wheel
Requires-Dist: Click (==7.0)
Requires-Dist: bcrypt (==3.1.7)
Requires-Dist: cryptography (==3.4.7)
Requires-Dist: paramiko (==2.6.0)
Requires-Dist: PyYAML (==5.3.1)
Requires-Dist: requests (==2.22.0)
Requires-Dist: cx-Oracle (==7.3.0)
Requires-Dist: lxml (==4.6.3)
Requires-Dist: SQLAlchemy (==1.4.27)
Requires-Dist: pandas (==1.3.4)
Requires-Dist: kivy
Requires-Dist: twine
